bgo/__init__.py
bgo/__main__.py
bgo/api.py
bgo/config.py
bgo/interface.py
bgo/utils.py
bgo/view/__init__.py
bgo/view/asciiart.py
bgo/view/formater.py
bgo/view/printer.py
bgo-0.1.6.dist-info/METADATA
bgo-0.1.6.dist-info/WHEEL
bgo-0.1.6.dist-info/entry_points.txt
bgo-0.1.6.dist-info/RECORD
