Metadata-Version: 2.1
Name: bgo
Version: 0.1.6
Summary: About
Author: bog (before going out) is sexy terminal util to view the weather
Requires-Python: >=3.11,<4.0
Classifier: Programming Language :: Python :: 3
Classifier: Programming Language :: Python :: 3.11
Classifier: Programming Language :: Python :: 3.12
Requires-Dist: pre-commit (>=3.6.2,<4.0.0)
Requires-Dist: python-dotenv (>=1.0.1,<2.0.0)
Requires-Dist: requests (>=2.31.0,<3.0.0)
Requires-Dist: rich (>=13.7.0,<14.0.0)
Requires-Dist: types-requests (>=2.31.0.20240218,<3.0.0.0)
